{
  "openapi": "3.0.0",
  "info": {
    "version": "v0.0.1",
    "title": "Documentasi API Ticket Portal",
    "description": "Applikasi untuk pembelian/pemesanan tiket dengan menggunakan MERN Stack"
  },
  "servers": [
    {
      "url": "http://localhost:5000/api",
      "description": "Development server"
    },
    {
      "url": "https://kasyaproject-ticket-portal-backend.vercel.app/api",
      "description": "Production server"
    }
  ],
  "paths": {
    "/auth/register": {
      "post": {
        "tags": [
          "Auth"
        ],
        "description": "",
        "responses": {
          "default": {
            "description": ""
          }
        },
        "requestBody": {
          "required": true,
          "content": {
            "application/json": {
              "schema": {
                "$ref": "#/components/schemas/RegisterRequest"
              }
            },
            "application/xml": {
              "schema": {
                "$ref": "#/components/schemas/RegisterRequest"
              }
            }
          }
        }
      }
    },
    "/auth/login": {
      "post": {
        "tags": [
          "Auth"
        ],
        "description": "",
        "responses": {
          "default": {
            "description": ""
          }
        },
        "requestBody": {
          "required": true,
          "content": {
            "application/json": {
              "schema": {
                "$ref": "#/components/schemas/LoginRequest"
              }
            },
            "application/xml": {
              "schema": {
                "$ref": "#/components/schemas/LoginRequest"
              }
            }
          }
        }
      }
    },
    "/auth/checkMe": {
      "get": {
        "tags": [
          "Auth"
        ],
        "description": "",
        "responses": {
          "default": {
            "description": ""
          }
        },
        "security": [
          {
            "bearerAuth": []
          }
        ]
      }
    },
    "/auth/activation": {
      "post": {
        "tags": [
          "Auth"
        ],
        "description": "",
        "responses": {
          "default": {
            "description": ""
          }
        },
        "requestBody": {
          "required": true,
          "content": {
            "application/json": {
              "schema": {
                "$ref": "#/components/schemas/ActivationRequest"
              }
            },
            "application/xml": {
              "schema": {
                "$ref": "#/components/schemas/ActivationRequest"
              }
            }
          }
        }
      }
    },
    "/auth/updateProfile": {
      "put": {
        "tags": [
          "Auth"
        ],
        "description": "",
        "responses": {
          "default": {
            "description": ""
          }
        },
        "security": [
          {
            "bearerAuth": []
          }
        ],
        "requestBody": {
          "required": true,
          "content": {
            "application/json": {
              "schema": {
                "$ref": "#/components/schemas/UpdateProfileRequest"
              }
            },
            "application/xml": {
              "schema": {
                "$ref": "#/components/schemas/UpdateProfileRequest"
              }
            }
          }
        }
      }
    },
    "/auth/updatePassword": {
      "put": {
        "tags": [
          "Auth"
        ],
        "description": "",
        "responses": {
          "default": {
            "description": ""
          }
        },
        "security": [
          {
            "bearerAuth": []
          }
        ],
        "requestBody": {
          "required": true,
          "content": {
            "application/json": {
              "schema": {
                "$ref": "#/components/schemas/UpdatePasswordRequest"
              }
            },
            "application/xml": {
              "schema": {
                "$ref": "#/components/schemas/UpdatePasswordRequest"
              }
            }
          }
        }
      }
    },
    "/events": {
      "post": {
        "tags": [
          "Events"
        ],
        "description": "",
        "responses": {
          "default": {
            "description": ""
          }
        },
        "security": [
          {
            "bearerAuth": {}
          }
        ],
        "requestBody": {
          "required": true,
          "content": {
            "application/json": {
              "schema": {
                "$ref": "#/components/schemas/EventRequest"
              }
            },
            "application/xml": {
              "schema": {
                "$ref": "#/components/schemas/EventRequest"
              }
            }
          }
        }
      },
      "get": {
        "tags": [
          "Events"
        ],
        "description": "",
        "parameters": [
          {
            "name": "search",
            "in": "query",
            "schema": {
              "type": "string"
            }
          },
          {
            "name": "limit",
            "in": "query",
            "default": 10,
            "schema": {
              "type": "number"
            }
          },
          {
            "name": "page",
            "in": "query",
            "default": 1,
            "schema": {
              "type": "number"
            }
          },
          {
            "name": "category",
            "in": "query",
            "schema": {
              "type": "string"
            }
          },
          {
            "name": "isOnline",
            "in": "query",
            "schema": {
              "type": "boolean"
            }
          },
          {
            "name": "isFetured",
            "in": "query",
            "schema": {
              "type": "boolean"
            }
          },
          {
            "name": "isPublish",
            "in": "query",
            "schema": {
              "type": "boolean"
            }
          }
        ],
        "responses": {
          "default": {
            "description": ""
          }
        }
      }
    },
    "/events/{id}": {
      "get": {
        "tags": [
          "Events"
        ],
        "description": "",
        "parameters": [
          {
            "name": "id",
            "in": "path",
            "required": true,
            "schema": {
              "type": "string"
            }
          }
        ],
        "responses": {
          "default": {
            "description": ""
          }
        }
      },
      "put": {
        "tags": [
          "Events"
        ],
        "description": "",
        "parameters": [
          {
            "name": "id",
            "in": "path",
            "required": true,
            "schema": {
              "type": "string"
            }
          }
        ],
        "responses": {
          "default": {
            "description": ""
          }
        },
        "security": [
          {
            "bearerAuth": {}
          }
        ],
        "requestBody": {
          "required": true,
          "content": {
            "application/json": {
              "schema": {
                "$ref": "#/components/schemas/EventRequest"
              }
            },
            "application/xml": {
              "schema": {
                "$ref": "#/components/schemas/EventRequest"
              }
            }
          }
        }
      },
      "delete": {
        "tags": [
          "Events"
        ],
        "description": "",
        "parameters": [
          {
            "name": "id",
            "in": "path",
            "required": true,
            "schema": {
              "type": "string"
            }
          }
        ],
        "responses": {
          "default": {
            "description": ""
          }
        },
        "security": [
          {
            "bearerAuth": {}
          }
        ]
      }
    },
    "/events/{slug}/slug": {
      "get": {
        "tags": [
          "Events"
        ],
        "description": "",
        "parameters": [
          {
            "name": "slug",
            "in": "path",
            "required": true,
            "schema": {
              "type": "string"
            }
          }
        ],
        "responses": {
          "default": {
            "description": ""
          }
        }
      }
    },
    "/category": {
      "post": {
        "tags": [
          "Category"
        ],
        "description": "",
        "responses": {
          "default": {
            "description": ""
          }
        },
        "security": [
          {
            "bearerAuth": {}
          }
        ],
        "requestBody": {
          "required": true,
          "content": {
            "application/json": {
              "schema": {
                "$ref": "#/components/schemas/CategoryRequest"
              }
            },
            "application/xml": {
              "schema": {
                "$ref": "#/components/schemas/CategoryRequest"
              }
            }
          }
        }
      },
      "get": {
        "tags": [
          "Category"
        ],
        "description": "",
        "parameters": [
          {
            "name": "page",
            "in": "query",
            "schema": {
              "type": "string"
            }
          },
          {
            "name": "limit",
            "in": "query",
            "schema": {
              "type": "string"
            }
          },
          {
            "name": "search",
            "in": "query",
            "schema": {
              "type": "string"
            }
          }
        ],
        "responses": {
          "default": {
            "description": ""
          }
        }
      }
    },
    "/category/{id}": {
      "get": {
        "tags": [
          "Category"
        ],
        "description": "",
        "parameters": [
          {
            "name": "id",
            "in": "path",
            "required": true,
            "schema": {
              "type": "string"
            }
          }
        ],
        "responses": {
          "default": {
            "description": ""
          }
        }
      },
      "put": {
        "tags": [
          "Category"
        ],
        "description": "",
        "parameters": [
          {
            "name": "id",
            "in": "path",
            "required": true,
            "schema": {
              "type": "string"
            }
          }
        ],
        "responses": {
          "default": {
            "description": ""
          }
        },
        "security": [
          {
            "bearerAuth": {}
          }
        ],
        "requestBody": {
          "required": true,
          "content": {
            "application/json": {
              "schema": {
                "$ref": "#/components/schemas/CategoryRequest"
              }
            },
            "application/xml": {
              "schema": {
                "$ref": "#/components/schemas/CategoryRequest"
              }
            }
          }
        }
      },
      "delete": {
        "tags": [
          "Category"
        ],
        "description": "",
        "parameters": [
          {
            "name": "id",
            "in": "path",
            "required": true,
            "schema": {
              "type": "string"
            }
          }
        ],
        "responses": {
          "default": {
            "description": ""
          }
        },
        "security": [
          {
            "bearerAuth": {}
          }
        ]
      }
    },
    "/media/upload-single": {
      "post": {
        "tags": [
          "Media"
        ],
        "description": "",
        "responses": {
          "default": {
            "description": ""
          }
        },
        "security": [
          {
            "bearerAuth": {}
          }
        ],
        "requestBody": {
          "required": true,
          "content": {
            "multipart/form-data": {
              "schema": {
                "type": "object",
                "properties": {
                  "file": {
                    "type": "string",
                    "format": "binary"
                  }
                }
              }
            }
          }
        }
      }
    },
    "/media/upload-multiple": {
      "post": {
        "tags": [
          "Media"
        ],
        "description": "",
        "responses": {
          "default": {
            "description": ""
          }
        },
        "security": [
          {
            "bearerAuth": {}
          }
        ],
        "requestBody": {
          "required": true,
          "content": {
            "multipart/form-data": {
              "schema": {
                "type": "object",
                "properties": {
                  "files": {
                    "type": "array",
                    "items": {
                      "type": "string",
                      "format": "binary"
                    }
                  }
                }
              }
            }
          }
        }
      }
    },
    "/media/remove": {
      "delete": {
        "tags": [
          "Media"
        ],
        "description": "",
        "responses": {
          "default": {
            "description": ""
          }
        },
        "security": [
          {
            "bearerAuth": {}
          }
        ],
        "requestBody": {
          "required": true,
          "content": {
            "application/json": {
              "schema": {
                "$ref": "#/components/schemas/RemoveMediaRequest"
              }
            },
            "application/xml": {
              "schema": {
                "$ref": "#/components/schemas/RemoveMediaRequest"
              }
            }
          }
        }
      }
    },
    "/regions": {
      "get": {
        "tags": [
          "Regions"
        ],
        "description": "",
        "responses": {
          "default": {
            "description": ""
          }
        }
      }
    },
    "/regions/{id}/province": {
      "get": {
        "tags": [
          "Regions"
        ],
        "description": "",
        "parameters": [
          {
            "name": "id",
            "in": "path",
            "required": true,
            "schema": {
              "type": "string"
            }
          }
        ],
        "responses": {
          "default": {
            "description": ""
          }
        }
      }
    },
    "/regions/{id}/regency": {
      "get": {
        "tags": [
          "Regions"
        ],
        "description": "",
        "parameters": [
          {
            "name": "id",
            "in": "path",
            "required": true,
            "schema": {
              "type": "string"
            }
          }
        ],
        "responses": {
          "default": {
            "description": ""
          }
        }
      }
    },
    "/regions/{id}/district": {
      "get": {
        "tags": [
          "Regions"
        ],
        "description": "",
        "parameters": [
          {
            "name": "id",
            "in": "path",
            "required": true,
            "schema": {
              "type": "string"
            }
          }
        ],
        "responses": {
          "default": {
            "description": ""
          }
        }
      }
    },
    "/regions/{id}/village": {
      "get": {
        "tags": [
          "Regions"
        ],
        "description": "",
        "parameters": [
          {
            "name": "id",
            "in": "path",
            "required": true,
            "schema": {
              "type": "string"
            }
          }
        ],
        "responses": {
          "default": {
            "description": ""
          }
        }
      }
    },
    "/regions-search": {
      "get": {
        "tags": [
          "Regions"
        ],
        "description": "",
        "parameters": [
          {
            "name": "name",
            "in": "query",
            "schema": {
              "type": "string"
            }
          }
        ],
        "responses": {
          "default": {
            "description": ""
          }
        }
      }
    },
    "/banners": {
      "post": {
        "tags": [
          "Banners"
        ],
        "description": "",
        "responses": {
          "default": {
            "description": ""
          }
        },
        "security": [
          {
            "bearerAuth": {}
          }
        ],
        "requestBody": {
          "required": true,
          "content": {
            "application/json": {
              "schema": {
                "$ref": "#/components/schemas/BannerRequest"
              }
            },
            "application/xml": {
              "schema": {
                "$ref": "#/components/schemas/BannerRequest"
              }
            }
          }
        }
      },
      "get": {
        "tags": [
          "Banners"
        ],
        "description": "",
        "parameters": [
          {
            "name": "limit",
            "in": "query",
            "schema": {
              "type": "string"
            }
          },
          {
            "name": "page",
            "in": "query",
            "schema": {
              "type": "string"
            }
          },
          {
            "name": "search",
            "in": "query",
            "schema": {
              "type": "string"
            }
          }
        ],
        "responses": {
          "default": {
            "description": ""
          }
        }
      }
    },
    "/banners/{id}": {
      "get": {
        "tags": [
          "Banners"
        ],
        "description": "",
        "parameters": [
          {
            "name": "id",
            "in": "path",
            "required": true,
            "schema": {
              "type": "string"
            }
          }
        ],
        "responses": {
          "default": {
            "description": ""
          }
        }
      },
      "put": {
        "tags": [
          "Banners"
        ],
        "description": "",
        "parameters": [
          {
            "name": "id",
            "in": "path",
            "required": true,
            "schema": {
              "type": "string"
            }
          }
        ],
        "responses": {
          "default": {
            "description": ""
          }
        },
        "security": [
          {
            "bearerAuth": {}
          }
        ],
        "requestBody": {
          "required": true,
          "content": {
            "application/json": {
              "schema": {
                "$ref": "#/components/schemas/BannerRequest"
              }
            },
            "application/xml": {
              "schema": {
                "$ref": "#/components/schemas/BannerRequest"
              }
            }
          }
        }
      },
      "delete": {
        "tags": [
          "Banners"
        ],
        "description": "",
        "parameters": [
          {
            "name": "id",
            "in": "path",
            "required": true,
            "schema": {
              "type": "string"
            }
          }
        ],
        "responses": {
          "default": {
            "description": ""
          }
        },
        "security": [
          {
            "bearerAuth": {}
          }
        ]
      }
    },
    "/tickets": {
      "post": {
        "tags": [
          "Tickets"
        ],
        "description": "",
        "responses": {
          "default": {
            "description": ""
          }
        },
        "security": [
          {
            "bearerAuth": {}
          }
        ],
        "requestBody": {
          "required": true,
          "content": {
            "application/json": {
              "schema": {
                "$ref": "#/components/schemas/TicketRequest"
              }
            },
            "application/xml": {
              "schema": {
                "$ref": "#/components/schemas/TicketRequest"
              }
            }
          }
        }
      },
      "get": {
        "tags": [
          "Tickets"
        ],
        "description": "",
        "parameters": [
          {
            "name": "limit",
            "in": "query",
            "schema": {
              "type": "string"
            }
          },
          {
            "name": "page",
            "in": "query",
            "schema": {
              "type": "string"
            }
          },
          {
            "name": "search",
            "in": "query",
            "schema": {
              "type": "string"
            }
          }
        ],
        "responses": {
          "default": {
            "description": ""
          }
        }
      }
    },
    "/tickets/{id}": {
      "get": {
        "tags": [
          "Tickets"
        ],
        "description": "",
        "parameters": [
          {
            "name": "id",
            "in": "path",
            "required": true,
            "schema": {
              "type": "string"
            }
          }
        ],
        "responses": {
          "default": {
            "description": ""
          }
        }
      },
      "put": {
        "tags": [
          "Tickets"
        ],
        "description": "",
        "parameters": [
          {
            "name": "id",
            "in": "path",
            "required": true,
            "schema": {
              "type": "string"
            }
          }
        ],
        "responses": {
          "default": {
            "description": ""
          }
        },
        "security": [
          {
            "bearerAuth": {}
          }
        ],
        "requestBody": {
          "required": true,
          "content": {
            "application/json": {
              "schema": {
                "$ref": "#/components/schemas/TicketRequest"
              }
            },
            "application/xml": {
              "schema": {
                "$ref": "#/components/schemas/TicketRequest"
              }
            }
          }
        }
      },
      "delete": {
        "tags": [
          "Tickets"
        ],
        "description": "",
        "parameters": [
          {
            "name": "id",
            "in": "path",
            "required": true,
            "schema": {
              "type": "string"
            }
          }
        ],
        "responses": {
          "default": {
            "description": ""
          }
        },
        "security": [
          {
            "bearerAuth": {}
          }
        ]
      }
    },
    "/tickets/{eventId}/events": {
      "get": {
        "tags": [
          "Tickets"
        ],
        "description": "",
        "parameters": [
          {
            "name": "eventId",
            "in": "path",
            "required": true,
            "schema": {
              "type": "string"
            }
          }
        ],
        "responses": {
          "default": {
            "description": ""
          }
        }
      }
    },
    "/orders": {
      "post": {
        "tags": [
          "Order"
        ],
        "description": "",
        "responses": {
          "default": {
            "description": ""
          }
        },
        "security": [
          {
            "bearerAuth": {}
          }
        ],
        "requestBody": {
          "required": true,
          "content": {
            "application/json": {
              "schema": {
                "$ref": "#/components/schemas/OrderRequest"
              }
            },
            "application/xml": {
              "schema": {
                "$ref": "#/components/schemas/OrderRequest"
              }
            }
          }
        }
      },
      "get": {
        "tags": [
          "Order"
        ],
        "description": "",
        "parameters": [
          {
            "name": "limit",
            "in": "query",
            "schema": {
              "type": "string"
            }
          },
          {
            "name": "page",
            "in": "query",
            "schema": {
              "type": "string"
            }
          },
          {
            "name": "search",
            "in": "query",
            "schema": {
              "type": "string"
            }
          }
        ],
        "responses": {
          "default": {
            "description": ""
          }
        },
        "security": [
          {
            "bearerAuth": {}
          }
        ]
      }
    },
    "/orders/{orderId}": {
      "get": {
        "tags": [
          "Order"
        ],
        "description": "",
        "parameters": [
          {
            "name": "orderId",
            "in": "path",
            "required": true,
            "schema": {
              "type": "string"
            }
          }
        ],
        "responses": {
          "default": {
            "description": ""
          }
        },
        "security": [
          {
            "bearerAuth": {}
          }
        ]
      },
      "delete": {
        "tags": [
          "Order"
        ],
        "description": "",
        "parameters": [
          {
            "name": "orderId",
            "in": "path",
            "required": true,
            "schema": {
              "type": "string"
            }
          }
        ],
        "responses": {
          "default": {
            "description": ""
          }
        },
        "security": [
          {
            "bearerAuth": {}
          }
        ]
      }
    },
    "/orders/{orderId}/completed": {
      "put": {
        "tags": [
          "Order"
        ],
        "description": "",
        "parameters": [
          {
            "name": "orderId",
            "in": "path",
            "required": true,
            "schema": {
              "type": "string"
            }
          }
        ],
        "responses": {
          "default": {
            "description": ""
          }
        },
        "security": [
          {
            "bearerAuth": {}
          }
        ]
      }
    },
    "/orders/{orderId}/pending": {
      "put": {
        "tags": [
          "Order"
        ],
        "description": "",
        "parameters": [
          {
            "name": "orderId",
            "in": "path",
            "required": true,
            "schema": {
              "type": "string"
            }
          }
        ],
        "responses": {
          "default": {
            "description": ""
          }
        },
        "security": [
          {
            "bearerAuth": {}
          }
        ]
      }
    },
    "/orders/{orderId}/cancelled": {
      "put": {
        "tags": [
          "Order"
        ],
        "description": "",
        "parameters": [
          {
            "name": "orderId",
            "in": "path",
            "required": true,
            "schema": {
              "type": "string"
            }
          }
        ],
        "responses": {
          "default": {
            "description": ""
          }
        },
        "security": [
          {
            "bearerAuth": {}
          }
        ]
      }
    },
    "/orders-history": {
      "get": {
        "tags": [
          "Order"
        ],
        "description": "",
        "parameters": [
          {
            "name": "limit",
            "in": "query",
            "schema": {
              "type": "string"
            }
          },
          {
            "name": "page",
            "in": "query",
            "schema": {
              "type": "string"
            }
          },
          {
            "name": "search",
            "in": "query",
            "schema": {
              "type": "string"
            }
          }
        ],
        "responses": {
          "default": {
            "description": ""
          }
        },
        "security": [
          {
            "bearerAuth": {}
          }
        ]
      }
    }
  },
  "components": {
    "securitySchemes": {
      "bearerAuth": {
        "type": "http",
        "scheme": "bearer"
      }
    },
    "schemas": {
      "LoginRequest": {
        "type": "object",
        "properties": {
          "identifier": {
            "type": "string",
            "example": "Admin123"
          },
          "password": {
            "type": "string",
            "example": "Admin123"
          }
        },
        "xml": {
          "name": "LoginRequest"
        }
      },
      "RegisterRequest": {
        "type": "object",
        "properties": {
          "fullname": {
            "type": "string",
            "example": "dika123123"
          },
          "username": {
            "type": "string",
            "example": "dika123123"
          },
          "email": {
            "type": "string",
            "example": "dika123123@gmail.com"
          },
          "password": {
            "type": "string",
            "example": "password123"
          },
          "confirmPassword": {
            "type": "string",
            "example": "password123"
          }
        },
        "xml": {
          "name": "RegisterRequest"
        }
      },
      "ActivationRequest": {
        "type": "object",
        "properties": {
          "code": {
            "type": "string",
            "example": "qwerty1234567890"
          }
        },
        "xml": {
          "name": "ActivationRequest"
        }
      },
      "UpdateProfileRequest": {
        "type": "object",
        "properties": {
          "fullname": {
            "type": "string",
            "example": "dika123123"
          },
          "profilePicture": {
            "type": "string",
            "example": "fileUrl"
          }
        },
        "xml": {
          "name": "UpdateProfileRequest"
        }
      },
      "UpdatePasswordRequest": {
        "type": "object",
        "properties": {
          "oldPassword": {
            "type": "string",
            "example": "oldPassword123"
          },
          "password": {
            "type": "string",
            "example": "newPassword123"
          },
          "confirmPassword": {
            "type": "string",
            "example": "newPassword123"
          }
        },
        "xml": {
          "name": "UpdatePasswordRequest"
        }
      },
      "EventRequest": {
        "type": "object",
        "properties": {
          "name": {
            "type": "string",
            "example": "Event - name"
          },
          "banner": {
            "type": "string",
            "example": "fileUrl"
          },
          "category": {
            "type": "string",
            "example": "Event - cat"
          },
          "description": {
            "type": "string",
            "example": "Event - desc"
          },
          "startDate": {
            "type": "string",
            "example": "yyyy-mm-dd hh:mm:ss"
          },
          "endDate": {
            "type": "string",
            "example": "yyyy-mm-dd hh:mm:ss"
          },
          "location": {
            "type": "object",
            "properties": {
              "region": {
                "type": "number",
                "example": 3273
              },
              "coordinate": {
                "type": "array",
                "example": [
                  0,
                  0
                ],
                "items": {
                  "type": "number"
                }
              },
              "address": {
                "type": "string",
                "example": "Event - address"
              }
            }
          },
          "isOnline": {
            "type": "boolean",
            "example": false
          },
          "isFetured": {
            "type": "boolean",
            "example": false
          },
          "isPublish": {
            "type": "boolean",
            "example": false
          }
        },
        "xml": {
          "name": "EventRequest"
        }
      },
      "CategoryRequest": {
        "type": "object",
        "properties": {
          "name": {
            "type": "string",
            "example": "Cat - name"
          },
          "description": {
            "type": "string",
            "example": "Cat - desc"
          },
          "icon": {
            "type": "string",
            "example": "Cat - icon"
          }
        },
        "xml": {
          "name": "CategoryRequest"
        }
      },
      "RemoveMediaRequest": {
        "type": "object",
        "properties": {
          "fileUrl": {
            "type": "string",
            "example": ""
          }
        },
        "xml": {
          "name": "RemoveMediaRequest"
        }
      },
      "BannerRequest": {
        "type": "object",
        "properties": {
          "title": {
            "type": "string",
            "example": "Banner - title"
          },
          "image": {
            "type": "string",
            "example": "fileUrl"
          },
          "isShow": {
            "type": "boolean",
            "example": true
          }
        },
        "xml": {
          "name": "BannerRequest"
        }
      },
      "TicketRequest": {
        "type": "object",
        "properties": {
          "event": {
            "type": "string",
            "example": "event id"
          },
          "name": {
            "type": "string",
            "example": "Ticket - name"
          },
          "description": {
            "type": "string",
            "example": "Ticket - desc"
          },
          "price": {
            "type": "number",
            "example": 100000
          },
          "quota": {
            "type": "number",
            "example": 100
          }
        },
        "xml": {
          "name": "TicketRequest"
        }
      },
      "OrderRequest": {
        "type": "object",
        "properties": {
          "events": {
            "type": "string",
            "example": "67ff7438897b242173fb5022 - ObjectId Event"
          },
          "ticket": {
            "type": "string",
            "example": "685ef1a3588a6a57a25b5a0f - ObjectId Ticket"
          },
          "quantity": {
            "type": "number",
            "example": 1
          }
        },
        "xml": {
          "name": "OrderRequest"
        }
      }
    }
  }
}